LICENSE
README.md
didcomm/__init__.py
didcomm/common/__init__.py
didcomm/common/algorithms.py
didcomm/common/resolvers.py
didcomm/common/types.py
didcomm/common/utils.py
didcomm/core/__init__.py
didcomm/core/anoncrypt.py
didcomm/core/authcrypt.py
didcomm/core/converters.py
didcomm/core/defaults.py
didcomm/core/from_prior.py
didcomm/core/keys/__init__.py
didcomm/core/keys/anoncrypt_keys_selector.py
didcomm/core/keys/authcrypt_keys_selector.py
didcomm/core/keys/forward_next_keys_selector.py
didcomm/core/keys/sign_keys_selector.py
didcomm/core/serialization.py
didcomm/core/sign.py
didcomm/core/types.py
didcomm/core/utils.py
didcomm/core/validation.py
didcomm/core/validators.py
didcomm/did_doc/__init__.py
didcomm/did_doc/did_doc.py
didcomm/did_doc/did_resolver.py
didcomm/did_doc/did_resolver_in_memory.py
didcomm/errors.py
didcomm/message.py
didcomm/pack_encrypted.py
didcomm/pack_plaintext.py
didcomm/pack_signed.py
didcomm/protocols/__init__.py
didcomm/protocols/routing/__init__.py
didcomm/protocols/routing/forward.py
didcomm/secrets/__init__.py
didcomm/secrets/secrets_resolver.py
didcomm/secrets/secrets_resolver_demo.py
didcomm/secrets/secrets_resolver_editable.py
didcomm/secrets/secrets_resolver_in_memory.py
didcomm/secrets/secrets_util.py
didcomm/unpack.py
didcomm-0.3.2.dist-info/LICENSE
didcomm-0.3.2.dist-info/METADATA
didcomm-0.3.2.dist-info/WHEEL
didcomm-0.3.2.dist-info/RECORD
