Metadata-Version: 2.1
Name: didcomm
Version: 0.3.2
Summary: Basic DIDComm v2 support in python
Home-page: https://github.com/sicpa-dlab/didcomm-python
License: Apache-2.0
Author: SICPA
Author-email: DLCHOpenSourceContrib@sicpa.com
Requires-Python: >=3.7,<4.0
Classifier: License :: OSI Approved :: Apache Software License
Classifier: Operating System :: OS Independent
Classifier: Programming Language :: Python :: 3
Classifier: Programming Language :: Python :: 3.7
Classifier: Programming Language :: Python :: 3.8
Classifier: Programming Language :: Python :: 3.9
Classifier: Programming Language :: Python :: 3.10
Classifier: Programming Language :: Python :: 3.11
Classifier: Programming Language :: Python :: 3
Classifier: Programming Language :: Python :: 3.7
Requires-Dist: Authlib (>=1.1.0,<2.0.0)
Requires-Dist: attrs (>=22.2,<23.0)
Requires-Dist: base58 (>=2.1,<3.0)
Requires-Dist: packaging (>=23.0,<24.0)
Requires-Dist: pycryptodomex (>=3.10,<4.0)
Requires-Dist: pydid (>=0.3.7,<0.4.0)
Requires-Dist: varint (>=1.0.2,<1.1.0)
Project-URL: Repository, https://github.com/sicpa-dlab/didcomm-python
